cloudshell/__init__.py
cloudshell/paloalto/__init__.py
cloudshell/paloalto/autoload/__init__.py
cloudshell/paloalto/autoload/panos_generic_snmp_autoload.py
cloudshell/paloalto/autoload/panos_if_table.py
cloudshell/paloalto/autoload/panos_snmp_system_info.py
cloudshell/paloalto/autoload/mibs/PAN-COMMON-MIB.json
cloudshell/paloalto/autoload/mibs/PAN-ENTITY-EXT-MIB.json
cloudshell/paloalto/autoload/mibs/PAN-GLOBAL-REG.json
cloudshell/paloalto/autoload/mibs/PAN-GLOBAL-TC.json
cloudshell/paloalto/autoload/mibs/PAN-PRODUCTS-MIB.json
cloudshell/paloalto/cli/__init__.py
cloudshell/paloalto/cli/panos_cli_configurator.py
cloudshell/paloalto/cli/panos_command_modes.py
cloudshell/paloalto/command_actions/__init__.py
cloudshell/paloalto/command_actions/enable_disable_snmp_actions.py
cloudshell/paloalto/command_actions/system_actions.py
cloudshell/paloalto/command_templates/__init__.py
cloudshell/paloalto/command_templates/configuration.py
cloudshell/paloalto/command_templates/enable_disable_snmp.py
cloudshell/paloalto/command_templates/firmware.py
cloudshell/paloalto/flows/__init__.py
cloudshell/paloalto/flows/panos_autoload_flow.py
cloudshell/paloalto/flows/panos_configuration_flow.py
cloudshell/paloalto/flows/panos_enable_disable_snmp_flow.py
cloudshell/paloalto/flows/panos_load_firmware_flow.py
cloudshell/paloalto/flows/panos_run_command_flow.py
cloudshell/paloalto/flows/panos_state_flow.py
cloudshell/paloalto/helpers/__init__.py
cloudshell/paloalto/helpers/temp_dir_context.py
cloudshell_paloalto-3.0.0.dist-info/licenses/LICENSE.htm
tests/__init__.py
tests/paloalto/__init__.py
tests/paloalto/command_actions/__init__.py
tests/paloalto/command_actions/test_system_actions.py
cloudshell_paloalto-3.0.0.dist-info/METADATA
cloudshell_paloalto-3.0.0.dist-info/WHEEL
cloudshell_paloalto-3.0.0.dist-info/top_level.txt
cloudshell_paloalto-3.0.0.dist-info/RECORD
