Metadata-Version: 2.4
Name: cloudshell-paloalto
Version: 3.0.0
Summary: Quali Palo Alto PanOS specific Package
Home-page: http://www.qualisystems.com/
Author: QualiSystems
Author-email: info@qualisystems.com
Requires-Python: ~=3.9
License-File: LICENSE.htm
Requires-Dist: tftpy
Requires-Dist: cloudshell-shell-core~=6.0
Requires-Dist: cloudshell-shell-standards~=2.0
Requires-Dist: cloudshell-shell-flows~=3.0
Requires-Dist: cloudshell-shell-connectivity-flow~=4.0
Requires-Dist: cloudshell-cli~=5.0
Requires-Dist: cloudshell-snmp~=5.0
Requires-Dist: cloudshell-snmp-autoload~=2.0
Requires-Dist: attrs<24,>=22
Requires-Dist: typing-extensions>=4.4
Dynamic: author
Dynamic: author-email
Dynamic: description
Dynamic: description-content-type
Dynamic: home-page
Dynamic: license-file
Dynamic: requires-dist
Dynamic: requires-python
Dynamic: summary
